odoo8_addon_delivery_carrier_label_postlogistics-8.0.1.1.1-py3.8-nspkg.pth
odoo_addons/delivery_carrier_label_postlogistics/README.rst
odoo_addons/delivery_carrier_label_postlogistics/__init__.py
odoo_addons/delivery_carrier_label_postlogistics/__openerp__.py
odoo_addons/delivery_carrier_label_postlogistics/company.py
odoo_addons/delivery_carrier_label_postlogistics/delivery.py
odoo_addons/delivery_carrier_label_postlogistics/delivery_data.xml
odoo_addons/delivery_carrier_label_postlogistics/delivery_view.xml
odoo_addons/delivery_carrier_label_postlogistics/res_config.py
odoo_addons/delivery_carrier_label_postlogistics/res_config_view.xml
odoo_addons/delivery_carrier_label_postlogistics/res_partner_data.xml
odoo_addons/delivery_carrier_label_postlogistics/stock.py
odoo_addons/delivery_carrier_label_postlogistics/stock_quant_package.py
odoo_addons/delivery_carrier_label_postlogistics/data/barcode_v2_1.wsdl
odoo_addons/delivery_carrier_label_postlogistics/data/barcode_v2_1.xsd
odoo_addons/delivery_carrier_label_postlogistics/data/barcode_v2_2.wsdl
odoo_addons/delivery_carrier_label_postlogistics/data/barcode_v2_2.xsd
odoo_addons/delivery_carrier_label_postlogistics/data/barcode_v2_2_wsbc.wsdl
odoo_addons/delivery_carrier_label_postlogistics/data/barcode_v2_2_wsbc.xsd
odoo_addons/delivery_carrier_label_postlogistics/data/post-barcode-handbuch.pdf
odoo_addons/delivery_carrier_label_postlogistics/i18n/am.po
odoo_addons/delivery_carrier_label_postlogistics/i18n/ar.po
odoo_addons/delivery_carrier_label_postlogistics/i18n/bg.po
odoo_addons/delivery_carrier_label_postlogistics/i18n/bs.po
odoo_addons/delivery_carrier_label_postlogistics/i18n/ca.po
odoo_addons/delivery_carrier_label_postlogistics/i18n/ca_ES.po
odoo_addons/delivery_carrier_label_postlogistics/i18n/cs.po
odoo_addons/delivery_carrier_label_postlogistics/i18n/da.po
odoo_addons/delivery_carrier_label_postlogistics/i18n/da_DK.po
odoo_addons/delivery_carrier_label_postlogistics/i18n/de.po
odoo8_addon_delivery_carrier_label_postlogistics-8.0.1.1.1.dist-info/METADATA
odoo8_addon_delivery_carrier_label_postlogistics-8.0.1.1.1.dist-info/WHEEL
odoo8_addon_delivery_carrier_label_postlogistics-8.0.1.1.1.dist-info/namespace_packages.txt
odoo8_addon_delivery_carrier_label_postlogistics-8.0.1.1.1.dist-info/top_level.txt
odoo8_addon_delivery_carrier_label_postlogistics-8.0.1.1.1.dist-info/RECORD
