Metadata-Version: 2.1
Name: odoo8-addon-delivery-carrier-label-postlogistics
Version: 8.0.1.1.1
Summary: PostLogistics Labels WebService
Home-page: http://www.camptocamp.com/
Author: Camptocamp,Odoo Community Association (OCA)
Author-email: support@odoo-community.org
License: AGPL-3
Platform: UNKNOWN
Classifier: Programming Language :: Python
Classifier: Framework :: Odoo
Classifier: Framework :: Odoo :: 8.0
Classifier: License :: OSI Approved :: GNU Affero General Public License v3
Requires-Python: ~=2.7
Requires-Dist: odoo8-addon-base-delivery-carrier-label
Requires-Dist: odoo (<9.0a,>=8.0a)
Requires-Dist: suds-jurko
